[{"testo_ean":9788829929337,"testo_titolo":"Chimica generale. Principi ed applicazioni moderne","testo_editore":"Piccin Editore","count":2168},{"testo_ean":9788808320971,"testo_titolo":"Principi di chimica. Con e-book","testo_editore":"Zanichelli","count":2077},{"testo_ean":9788838695391,"testo_titolo":"Chimica. La natura molecolare della materia e delle sue trasformazioni. Con Connect","testo_editore":"McGraw-Hill Education","count":1965},{"testo_ean":9783662517581,"testo_titolo":"Scientific Computing with MATLAB and Octave","testo_editore":"Springer","count":1962},{"testo_ean":9788867890095,"testo_titolo":"Lezioni di analisi matematica 1","testo_editore":"Celid","count":1910},{"testo_ean":9788879924283,"testo_titolo":"Analisi matematica 1. Appunti delle lezioni","testo_editore":"CLUT","count":1910},{"testo_ean":9780980232776,"testo_titolo":"Introduction to Linear Algebra","testo_editore":"Wellesley-Cambridge Press","count":1902},{"testo_ean":9788879922654,"testo_titolo":"Metodi e algoritmi per il calcolo numerico","testo_editore":"CLUT","count":1891},{"testo_ean":9788879922128,"testo_titolo":"Laboratorio di calcolo numerico. Esercizi di calcolo numerico risolti con Matlab","testo_editore":"CLUT","count":1869},{"testo_ean":9788847009226,"testo_titolo":"Analisi matematica 1. Teoria ed esercizi con complementi in rete","testo_editore":"Springer","count":1779},{"testo_ean":9788840813479,"testo_titolo":"Fondamenti di chimica. Con esercizi","testo_editore":"Cea","count":1773},{"testo_ean":9788838786075,"testo_titolo":"Algebra lineare","testo_editore":"Apogeo Maggioli","count":1769},{"testo_ean":9788879599597,"testo_titolo":"Fondamenti di chimica. Con contenuto digitale fornito elettronicamente","testo_editore":"Edises","count":1766},{"testo_ean":9788879595049,"testo_titolo":"Elementi di stechiometria","testo_editore":"Edises","count":1751},{"testo_ean":9788882180348,"testo_titolo":"Lezioni di geometria vol.2. Geometria analitica","testo_editore":"Levrotto e Bella","count":1748},{"testo_ean":9788882180409,"testo_titolo":"Lezioni di geometria vol.1. Algebra lineare","testo_editore":"Levrotto e Bella","count":1748},{"testo_ean":9788874885893,"testo_titolo":"Allenamenti di geometria. Esercizi e giochi di algebra lineare e geometria","testo_editore":"Esculapio","count":1743},{"testo_ean":9788867891269,"testo_titolo":"Lezioni di geometria","testo_editore":"Celid","count":1743},{"testo_ean":9788867891245,"testo_titolo":"Lezioni di algebra lineare. Con esercizi svolti","testo_editore":"Celid","count":1743},{"testo_ean":9788879923682,"testo_titolo":"Chiss\u00e0 chi lo sa. I quiz dell'esame di geometria","testo_editore":"CLUT","count":1743},{"testo_ean":9788879923439,"testo_titolo":"Lezioni di algebra lineare e geometria. I veri appunti del corso","testo_editore":"CLUT","count":1743},{"testo_ean":9788813211509,"testo_titolo":"Fondamenti di chimica per ingegneria","testo_editore":"Wolters Kluwer \u2013 Cedam","count":1672},{"testo_ean":9788808480057,"testo_titolo":"Principi fondamentali dell'assistenza infermieristica. (Volume unico)","testo_editore":"Cea","count":1671},{"testo_ean":9788876619311,"testo_titolo":"50 quiz di geometria","testo_editore":"Celid","count":1667},{"testo_ean":9788808187840,"testo_titolo":"Brunner-Suddarth. Infermieristica medico-chirurgica vol.1","testo_editore":"Cea","count":1567},{"testo_ean":9788879591379,"testo_titolo":"Fisica vol.1. Meccanica e termodinamica","testo_editore":"EdiSes","count":1514},{"testo_ean":9788833190259,"testo_titolo":"Anatomia umana","testo_editore":"Edises","count":1371},{"testo_ean":9788891635433,"testo_titolo":"Concetti di informatica e fondamenti di Python","testo_editore":"Apogeo Maggioli","count":1335},{"testo_ean":9788808580030,"testo_titolo":"Diagnosi infermieristiche. Applicazione alla pratica clinica","testo_editore":"Zanichelli","count":1124},{"testo_ean":9788808187901,"testo_titolo":"Brunner-Suddarth. Infermieristica medico-chirurgica vol.2","testo_editore":"Cea","count":1121},{"testo_ean":9788879924429,"testo_titolo":"LAG the Written Exam vol.1. Samples and Solutions v1","testo_editore":"CLUT","count":1100},{"testo_ean":9788879924610,"testo_titolo":"LAG the written exam vol.2. Samples and solutions v2","testo_editore":"CLUT","count":1100},{"testo_ean":9781259644030,"testo_titolo":"Harrison's Principles of Internal Medicine. (2 volumi)","testo_editore":"McGraw-Hill Education","count":1070},{"testo_ean":9788806219222,"testo_titolo":"Armi, acciaio e malattie. Breve storia del mondo negli ultimi tredicimila anni. Introduzione di Luca Cavalli-Sforza e Francesco Cavalli-Sforza","testo_editore":"Einaudi","count":1057},{"testo_ean":9788829929672,"testo_titolo":"Patologia generale e fisiopatologia generale vol.2","testo_editore":"Piccin Editore","count":1036},{"testo_ean":9788891909732,"testo_titolo":"Fisiologia umana. Un approccio integrato. Edizioni MyLab. Con contenuto digitale per download e accesso on line","testo_editore":"Pearson","count":1026},{"testo_ean":9788806239732,"testo_titolo":"Il pianeta umano. Come abbiamo creato l\u2019Antropocene","testo_editore":"Einaudi","count":989},{"testo_ean":9788808920690,"testo_titolo":"I principi di biochimica di Lehninger. Con e-book","testo_editore":"Zanichelli","count":973},{"testo_ean":9788891901651,"testo_titolo":"Il linguaggio C. Fondamenti e tecniche di programmazione. Ediz. mylab. Con espansione online","testo_editore":"Pearson","count":932},{"testo_ean":9788808637086,"testo_titolo":"Analisi matematica 2","testo_editore":"Zanichelli","count":916},{"testo_ean":9788808182159,"testo_titolo":"Fisica generale. Meccanica e termodinamica. Con contenuto digitale","testo_editore":"Cea","count":896},{"testo_ean":9788808151339,"testo_titolo":"Analisi matematica 1","testo_editore":"Zanichelli","count":875},{"testo_ean":9788865151358,"testo_titolo":"Ginecologia e ostetricia. (4 volumi)","testo_editore":"SEU","count":849},{"testo_ean":9788808723284,"testo_titolo":"Introduzione alla biochimica di Lehninger. Con e-book","testo_editore":"Zanichelli","count":824},{"testo_ean":9788829927913,"testo_titolo":"Biochimica medica. Strutturale metabolica e funzionale","testo_editore":"Piccin Editore","count":822},{"testo_ean":9788808820372,"testo_titolo":"Harrison. Principi di medicina interna. (2 volumi). Con e-book","testo_editore":"Cea","count":811},{"testo_ean":9788821449697,"testo_titolo":"Netter. Atlante di anatomia umana","testo_editore":"Edra","count":796},{"testo_ean":9788879599726,"testo_titolo":"Fisiologia","testo_editore":"Edises","count":776},{"testo_ean":9788829929122,"testo_titolo":"Elementi di patologia generale e fisiopatologia generale. Per corsi di laurea in professioni sanitarie","testo_editore":"Piccin Editore","count":775},{"testo_ean":9788829929634,"testo_titolo":"Patologia generale e fisiopatologia generale vol.1","testo_editore":"Piccin Editore","count":741}]